streamback/__init__.py
streamback/callbacks.py
streamback/context.py
streamback/events.py
streamback/exceptions.py
streamback/feedback_lane.py
streamback/listener.py
streamback/message.py
streamback/process_manager.py
streamback/retry_strategy.py
streamback/router.py
streamback/scheduler.py
streamback/streamback.py
streamback/streams.py
streamback/topic_process_messages.py
streamback/utils.py
streamback/extensions/__init__.py
streamback/extensions/auto_restart.py
streamback/extensions/stats.py
streamback/futures/__init__.py
streamback/futures/future.py
streamback/futures/runner.py
streamback/futures/serializers.py
streamback-0.5.0.dist-info/LICENCE.txt
streamback-0.5.0.dist-info/METADATA
streamback-0.5.0.dist-info/WHEEL
streamback-0.5.0.dist-info/top_level.txt
streamback-0.5.0.dist-info/RECORD
