Metadata-Version: 2.1
Name: streamback
Version: 0.5.0
Summary: Two way streams for your microservices
Author: Stefanos Liakis
Author-email: stliakis@gmail.com
Classifier: License :: OSI Approved :: MIT License
Classifier: Programming Language :: Python :: 3.6
License-File: LICENCE.txt
Requires-Dist: redis (>=2.10.6)
Requires-Dist: confluent-kafka (>=1.7.0)
Requires-Dist: psutil (>=5.8.0)
